setup.cfg
setup.py
staccato/__init__.py
staccato/twitter.py
staccato/utils.py
staccato.egg-info/PKG-INFO
staccato.egg-info/SOURCES.txt
staccato.egg-info/dependency_links.txt
staccato.egg-info/requires.txt
staccato.egg-info/top_level.txt