Metadata-Version: 1.0
Name: staccato
Version: 0.1.1
Summary: Twitter API wrapper for python 3
Home-page: UNKNOWN
Author: minamorl
Author-email: UNKNOWN
License: UNKNOWN
Platform: UNKNOWN
